cornish/__init__.py
cornish/ast_object.py
cornish/constants.py
cornish/exc.py
cornish/version.py
cornish-1.1.dist-info/METADATA
cornish-1.1.dist-info/WHEEL
cornish-1.1.dist-info/top_level.txt
cornish-1.1.dist-info/RECORD
