Metadata-Version: 2.1
Name: cornish
Version: 1.1
Summary: A pure Python interface to the excellent Starlink AST library.
Home-page: https://github.com/demitri/cornish
Author: Demitri Muna
Author-email: demitri@trillianverse.org
License: UNKNOWN
Project-URL: Documentation, https://github.com/demitri/cornish
Project-URL: Source Code, https://github.com/demitri/cornish
Platform: UNKNOWN
Requires-Python: >=3.6
Requires-Dist: starlink-pyast (>=3.15.3)
